{
    "[LENDRIVE] Otonari no Tenshi S2 - 01 [1080p HEVC 10bit][Dualsubs].mkv": {
        "duration": "23 min",
        "resolution": "1080p"
    },
    "[LENDRIVE] Otonari no Tenshi S2 - 02 [1080p HEVC 10bit][Dualsubs].mkv": {
        "duration": "23 min",
        "resolution": "1080p"
    },
    "[LENDRIVE] Otonari no Tenshi S2 - 03 [1080p HEVC 10bit][Dualsubs].mkv": {
        "duration": "23 min",
        "resolution": "1080p"
    },
    "[LENDRIVE] Otonari no Tenshi S2 - 04 [1080p HEVC 10bit][Dualsubs].mkv": {
        "duration": "23 min",
        "resolution": "1080p"
    },
    "[LENDRIVE] Otonari no Tenshi S2 - 05 [1080p HEVC 10bit][Dualsubs].mkv": {
        "duration": "23 min",
        "resolution": "1080p"
    },
    "[LENDRIVE] Otonari no Tenshi S2 - 06 [1080p HEVC 10bit][Dualsubs].mkv": {
        "duration": "23 min",
        "resolution": "1080p"
    },
    "[LENDRIVE] Otonari no Tenshi S2 - 07 [1080p HEVC 10bit][Dualsubs].mkv": {
        "duration": "23 min",
        "resolution": "1080p"
    },
    "[LENDRIVE] Otonari no Tenshi S2 - 08 [1080p HEVC 10bit][Dualsubs].mkv": {
        "duration": "23 min",
        "resolution": "1080p"
    },
    "[LENDRIVE] Otonari no Tenshi S2 - 09 [1080p HEVC 10bit][Dualsubs].mkv": {
        "duration": "23 min",
        "resolution": "1080p"
    },
    "[LENDRIVE] Otonari no Tenshi S2 - 10 [1080p HEVC 10bit][Dualsubs].mkv": {
        "duration": "23 min",
        "resolution": "1080p"
    },
    "[LENDRIVE] Otonari no Tenshi S2 - 11 [1080p HEVC 10bit][Dualsubs].mkv": {
        "duration": "23 min",
        "resolution": "1080p"
    }
}